{
    "version"      : "0.9.19.1 #01",
    "name"         : "Gox ModPack",
    "author"       : "GOX",
    "link"         : "http://www.goxwot.net/",
    "date"         : "05.07.2017",
    "image"        : true,
    "imageName"    : "gox_09191_01.png",
    "imageLink"    : "https://vignette1.wikia.nocookie.net/mixels/images/2/21/41536_GOX_a.png/revision/latest/scale-to-width-down/300?cb=20160705184756",
    "imageWidth"   : 300,
    "imageHeight"  : 300,
    "messageLinkName"  : "Get Details",
    "windowName"  : "Update Available",
    "buttonNameOpen"  : "Open",
    "buttonNameClose"  : "Close",
    "header"       : "<textformat><font color=\"#00ffff\">Modpack {name} by <b>{author}</b></font><br/><font color=\"#E2D2A2\">New version avaliable:<br/>{name}: </font><font color=\"#00ffff\">{version}</font> <font color=\"#02C9B3\">({date})</font><br/><font color=\"#FE0E00\"><b>Dont forget update!</b></textformat>",
    "message"      : "<font color=\"#E2D2A2\">ChangeLog:</font><br/><font color=\"#FE0E00\">We publish first release! :)</font>"
}